examples/__init__.py
examples/example_bls_multisig.py
examples/example_grpc_get_blockchain_info.py
examples/example_grpc_get_node_info.py
examples/example_jsonrpc_get_blockchain_info.py
examples/example_jsonrpc_get_node_info.py
examples/example_key_generation.py
examples/example_transfer_transaction_bls.py
examples/example_transfer_transaction_ed25519.py
examples/example_zmq.py
pactus/__init__.py
pactus/amount.py
pactus/crypto/__init__.py
pactus/crypto/address.py
pactus/crypto/crypto.py
pactus/crypto/private_key.py
pactus/crypto/public_key.py
pactus/crypto/signature.py
pactus/crypto/bls/__init__.py
pactus/crypto/bls/hash.py
pactus/crypto/bls/private_key.py
pactus/crypto/bls/public_key.py
pactus/crypto/bls/signature.py
pactus/crypto/bls/bls12_381/__init__.py
pactus/crypto/bls/bls12_381/bls_pop_g1.py
pactus/crypto/bls/bls12_381/bls_pop_g2.py
pactus/crypto/bls/bls12_381/bls_sig_g1.py
pactus/crypto/bls/bls12_381/bls_sig_g2.py
pactus/crypto/bls/bls12_381/consts.py
pactus/crypto/bls/bls12_381/curve_ops.py
pactus/crypto/bls/bls12_381/fields.py
pactus/crypto/bls/bls12_381/hash_to_field.py
pactus/crypto/bls/bls12_381/opt_swu_g1.py
pactus/crypto/bls/bls12_381/opt_swu_g2.py
pactus/crypto/bls/bls12_381/pairing.py
pactus/crypto/bls/bls12_381/serdesZ.py
pactus/crypto/bls/bls12_381/util.py
pactus/crypto/ed25519/__init__.py
pactus/crypto/ed25519/private_key.py
pactus/crypto/ed25519/public_key.py
pactus/crypto/ed25519/signature.py
pactus/encoding/__init__.py
pactus/encoding/encoding.py
pactus/transaction/__init__.py
pactus/transaction/_payload.py
pactus/transaction/transaction.py
pactus/utils/__init__.py
pactus/utils/bech32m.py
pactus/utils/utils.py
pactus_sdk-1.2.4.dist-info/licenses/LICENSE
pactus_sdk-1.2.4.dist-info/METADATA
pactus_sdk-1.2.4.dist-info/WHEEL
pactus_sdk-1.2.4.dist-info/top_level.txt
pactus_sdk-1.2.4.dist-info/RECORD
