Metadata-Version: 2.4
Name: pactus-sdk
Version: 1.2.4
Summary: Pactus Development Kit
Home-page: https://github.com/pactus-project/python-sdk
Author: Pactus Development Team
Author-email: info@pactus.org
License: MIT
Keywords: pactus,blockchain,sdk,web3,dapp,bls,bech32
Classifier: Development Status :: 5 - Production/Stable
Classifier: Intended Audience :: Developers
Classifier: Operating System :: OS Independent
Requires-Python: >=3.6
License-File: LICENSE
Requires-Dist: pactus-grpc>=1.7.4
Requires-Dist: pactus-jsonrpc>=1.7.4
Requires-Dist: ripemd-hash
Requires-Dist: grpcio
Requires-Dist: grpcio-tools
Requires-Dist: cryptography>=43.0
Requires-Dist: zmq
Dynamic: author
Dynamic: author-email
Dynamic: classifier
Dynamic: description
Dynamic: description-content-type
Dynamic: home-page
Dynamic: keywords
Dynamic: license
Dynamic: license-file
Dynamic: requires-dist
Dynamic: requires-python
Dynamic: summary
